superspreader/__init__.py
superspreader/exceptions.py
superspreader/fields.py
superspreader/i18n.py
superspreader/messages.py
superspreader/sheets.py
superspreader-0.2.7.2.dist-info/LICENSE.txt
superspreader-0.2.7.2.dist-info/METADATA
superspreader-0.2.7.2.dist-info/WHEEL
superspreader-0.2.7.2.dist-info/top_level.txt
superspreader-0.2.7.2.dist-info/RECORD
