Metadata-Version: 2.1
Name: superspreader
Version: 0.2.7.2
Summary: Load data from spreadsheets easily
Home-page: https://github.com/julianklotz/superspreader
Author: Julian Klotz
Author-email: post@julianklotz.de
Project-URL: Source, https://github.com/julianklotz/superspreader
Keywords: excel,spreadsheets,import,csv,tsv,openpyxl
Classifier: Intended Audience :: Developers
Classifier: License :: OSI Approved :: MIT License
Classifier: Programming Language :: Python :: 3
Classifier: Programming Language :: Python :: 3.7
Classifier: Programming Language :: Python :: 3.8
Classifier: Programming Language :: Python :: 3.9
Classifier: Programming Language :: Python :: 3.10
Classifier: Programming Language :: Python :: 3.11
Classifier: Programming Language :: Python :: 3 :: Only
Requires-Python: >=3.6, <4
License-File: LICENSE.txt
Requires-Dist: openpyxl (>=3)
Provides-Extra: dev
Requires-Dist: pre-commit ; extra == 'dev'
Provides-Extra: test
Requires-Dist: coverage ; extra == 'test'
